{
    "name": "Roboticket",
    "tokenColors": [
        {
            "name": "Comments",
            "scope": [
                "comment"
            ],
            "settings": {
                "foreground": "#AD95AF"
            }
        },
        {
            "name": "Comments: Preprocessor",
            "scope": "comment.block.preprocessor",
            "settings": {
                "fontStyle": "",
                "foreground": "#F5F5F5"
            }
        },
        {
            "name": "Comments: Documentation",
            "scope": [
                "comment.documentation",
                "comment.block.documentation"
            ],
            "settings": {
                "foreground": "#F5F5F5"
            }
        },
        {
            "name": "Invalid - Deprecated",
            "scope": "invalid.deprecated",
            "settings": {
                "foreground": "#FF8C00"
            }
        },
        {
            "name": "Invalid - Illegal",
            "scope": "invalid.illegal",
            "settings": {
                "foreground": "#FF8C00"
            }
        },
        {
            "name": "Keywords",
            "scope": [
                "keyword.other",
                "keyword.control",
                "punctuation.section.group",
                "punctuation.section.braces"
            ],
            "settings": {
                "foreground": "#295F94"
            }
        },
        {
            "name": "Types",
            "scope": [
                "storage.type"
            ],
            "settings": {
                "foreground": "#295F94"
            }
        },
        {
            "name": "Language Constants",
            "scope": [
                "constant.language",
                "support.constant",
                "variable.language"
            ],
            "settings": {
                "foreground": "#55AA55"
            }
        },
        {
            "name": "Variables",
            "scope": [
                "variable",
                "support.variable",
                "punctuation.definition.variable"
            ],
            "settings": {
                "foreground": "#55AA55"
            }
        },
        {
            "name": "Tag attribute",
            "scope": [
                "entity.other.attribute-name",
                "variable.parameter",
                "keyword.operator",
                "meta"
            ],
            "settings": {
                "fontStyle": "",
                "foreground": "#000000"

            }
        },
        {
            "name": "Functions",
            "scope": [
                "entity.name.function"
            ],
            "settings": {
                "foreground": "#AF0F91"
            }
        },
        {
            "name": "Functions2",
            "scope": [
                "support.function"
            ],
            "settings": {
                "foreground": "#BC5A65"
            }
        },
        {
            "name": "Classes",
            "scope": [
                "entity.name.tag",
                "entity.name.type",
                "entity.other.inherited-class",
                "support.class"
            ],
            "settings": {
                "foreground": "#295F94"
            }
        },
        {
            "name": "Exceptions",
            "scope": "entity.name.exception",
            "settings": {
                "foreground": "#FF0000"
            }
        },
        {
            "name": "Sections",
            "scope": "entity.name.section",
            "settings": {
            }
        },
        {
            "name": "Numbers, Characters",
            "scope": [
                "constant.numeric",
                "constant"
            ],
            "settings": {
                "foreground": "#AF0F91"
            }
        },
        {
            "name": "User-defined constant",
            "scope": [
                "constant.character",
                "constant.other"
            ],
            "settings": {
                "foreground": "#295F94"
            }
        },
        {
            "name": "Strings",
            "scope": "string",
            "settings": {
                "foreground": "#317ECC"
            }
        },
        {
            "name": "Strings: Escape Sequences",
            "scope": "constant.character.escape",
            "settings": {
                "foreground": "#317ECC"
            }
        },
        {
            "name": "Strings: Regular Expressions",
            "scope": "string.regexp",
            "settings": {
                "foreground": "#317ECC"
            }
        },
        {
            "name": "Strings: Symbols",
            "scope": "constant.other.symbol",
            "settings": {
                "foreground": "#317ECC"
            }
        }
    ],
    "colors": {
        "titleBar.activeBackground": "#F5F5F5",
        "titleBar.activeForeground": "#000000",
"tab.activeBackground": "#E1E1E1",
"tab.activeForeground": "#141414",
"tab.inactiveBackground": "#FFFFFF",
"tab.inactiveForeground": "#000000",
"editor.background": "#F5F5F5",
        "editor.foreground": "#000000",
"activityBar.background": "#FFFFFF",
        "activityBar.foreground": "#000000",
"sideBar.background": "#E1E1E1",
"statusBar.background": "#FFFFFF"
    }
}
